dstdsv/__about__.py
dstdsv/__init__.py
dstdsv/utils/__init__.py
dstdsv/utils/list_devices.py
dstdsv/utils/test_measure.py
dstdsv-0.1.1.dist-info/METADATA
dstdsv-0.1.1.dist-info/WHEEL
dstdsv-0.1.1.dist-info/licenses/LICENSE.txt
dstdsv-0.1.1.dist-info/RECORD
