Metadata-Version: 2.3
Name: dstdsv
Version: 0.1.1
Summary: Python driver for IMADA DST/DSV Force gauges
Project-URL: Documentation, https://github.com/fdmysterious/dstdsv#readme
Project-URL: Issues, https://github.com/fdmysterious/dstdsv/issues
Project-URL: Source, https://github.com/fdmysterious/dstdsv
Author-email: Florian Dupeyron <florian.dupeyron@mugcat.fr>
License-Expression: MIT
License-File: LICENSE.txt
Classifier: Development Status :: 4 - Beta
Classifier: Programming Language :: Python
Classifier: Programming Language :: Python :: 3.8
Classifier: Programming Language :: Python :: 3.9
Classifier: Programming Language :: Python :: 3.10
Classifier: Programming Language :: Python :: 3.11
Classifier: Programming Language :: Python :: 3.12
Classifier: Programming Language :: Python :: Implementation :: CPython
Classifier: Programming Language :: Python :: Implementation :: PyPy
Requires-Python: >=3.8
Requires-Dist: pyserial==3.5
